Workbook

Sheet P&L факт
C1: Апрель 2026 | F1: Май 2026 | I1: Июнь 2026
C2: PROFIT
A3: Продукт и канал продаж | C3: Стоимость единицы | D3: Количество единиц | E3: Сумма | F3: Стоимость единицы | G3: Количество единиц | H3: Сумма | I3: Стоимость единицы | J3: Количество единиц | K3: Сумма
A4: Породажи на OZON: боксы для пересадки
A5: Детализация | B5: Антуриум 1,2
B6: Антуриум 2,2
B7: Аглаонема 1,2
B8: Аглаонема 2,2
B9: Эпипремнум 1,2
B10: Эпипремнум 2,2
B11: Спатифиллум 1,2
B12: Спатифиллум 2,2
B13: Спатифиллум 3,5
B14: Замиакулькас 1,2
B15: Замиакулькас 2,2
B16: Замиакулькас 3,5
B17: Монстера 2,2
... B20: Фикус 3,5
C21: LOSS
A22: EBT | C22: =C24+C66+C73+C75+C89 -> 332644.12
A23: Статья расхода | C23: Стоимость единицы | D23: Количество единиц (штуки/литры) | E23: Сумма | F23: Стоимость единицы | G23: Количество единиц | H23: Сумма | I23: Стоимость единицы | J23: Количество единиц | K23: Сумма
A24: Продуктовые расходы | C24: =SUM(E25:E58,C65) -> 187284.12
A25: Почвосмесь | B25: Торф нейтральный | C25: =E25/D25 -> 18.576 | D25: =200+50 -> 250 | E25: =2812+1832 -> 4644
B26: Торф кислый | C26: =E26/D26 -> 20.066667 | D26: =50+10 -> 60 | E26: =665+539 -> 1204
B27: Кокосовый субстрат | C27: =E27/D27 -> 67 | D27: =50+50 -> 100 | E27: =3451+3249 -> 6700
B28: Диатомит | C28: =E28/D28 -> 92.342857 | D28: =20+10+40 -> 70 | E28: =1810+1054+3600 -> 6464
B29: Цеолит вулканический | C29: =E29/D29 -> 162.04615 | D29: =60+10+60 -> 130 | E29: =12000+1428+7638 -> 21066
B30: Мох сфагнум | C30: =E30/D30 -> 115.5 | D30: =12+12+12+12 -> 48 | E30: =1305+1641+2598 -> 5544
B31: Уголь | C31: =E31/D31 -> 112.30769 | D31: =45+10+18+18 -> 91 | E31: =4194+990+5036 -> 10220
B32: Биогумус | C32: =E32/D32 -> 90 | D32: 30 | E32: 2700
B33: Пеностекло | C33: =E33/D33 -> 88.558442 | D33: =40+14+5+18 -> 77 | E33: =2628+615+990+661+1925 -> 6819
B34: Кора сосновая Мелкая | C34: =E34/D34 -> 80 | D34: 40 | E34: 3200
B35: Кора сосновая Крупная | C35: =E35/D35 -> 110 | D35: 20 | E35: 2200
B36: Песок кварцевый 2-5 мм | C36: =E36/D36 -> 84.381818 | D36: =25+10+20 -> 55 | E36: =2052+877+1712 -> 4641
B37: Дренаж 10-20 мм | C37: =E37/D37 -> 58 | D37: =48+24+24+10 -> 106 | E37: =2616+1360+1339+833 -> 6148
A38: Допы | B38: Перчатки M | C38: =E38/D38 -> 10.061818 | D38: =50*11 -> 550 | E38: =455+3288+1341+450 -> 5534
B39: Корневин, 5г | C39: =E39/D39 -> 23.414815 | D39: =200+70 -> 270 | E39: =4600+1722 -> 6322
A40: Упаковка | B40: Квадропак Ц 110+60x190 | C40: =E40/D40 -> 12.05 | D40: =150+550 -> 700 | E40: =1807.5+6627.5 -> 8435
B41: Квадропак Ц 135+65х225 | C41: =E41/D41 -> 15.57 | D41: 200 | E41: 3114
B42: Квадропак П 135+65х225 | C42: =E42/D42 -> 15.57 | D42: =50+200 -> 250 | E42: =778.5+3114 -> 3892.5
B43: Квадропак П 150+90х250 | C43: =E43/D43 -> 19.34 | D43: =100+250 -> 350 | E43: =1934+4835 -> 6769
B44: Квадропак П 150+90х345 | C44: =E44/D44 -> 22.86 | D44: =50+150 -> 200 | E44: =1143+3429 -> 4572
B45: Коробка 200×200×100 | C45: =E45/D45 -> 39.3 | D45: 248 | E45: 9746.4
B46: Коробка 250×250×100 | C46: =E46/D46 -> 45.8 | D46: 110 | E46: 5038
B47: Коробка 320х220х100 | C47: 56.46
B48: Конверт | C48: =E48/D48 -> 12.231034 | D48: =20*29 -> 580 | E48: =6696+150+248 -> 7094
B49: Сотовая крафт-бумага | C49: =E49/D49 -> 29.495238 | D49: =(20*5)+5 -> 105 | E49: =2860+237 -> 3097
B50: Скотч-стикер круглый | C50: =E50/D50 -> 0.43 | D50: 1000 | E50: 430
B51: Курьерский пакет 240х320 | C51: =E51/D51 -> 2.7 | D51: 200 | E51: 540
B52: Курьерский пакет 300х400 | C52: =E52/D52 -> 3.5 | D52: 400 | E52: 1400
B53: Курьерский пакет 340х460 | C53: =E53/D53 -> 9.55 | D53: 100 | E53: 955
B54: Стикер для штрихкода mini | C54: =E54/D54 -> 0.1835 | D54: 2000 | E54: 367
B55: Коробка для отгрузки 600х400х400 | C55: =E55/D55 -> 73.07 | D55: 46 | E55: 3361.22
B56: Стикер для штрихкода maxi | C56: =E56/D56 -> 0.55333333 | D56: 300 | E56: 166
B57: Скотч
A58: Бренд | B58: Велком-листовка | C58: =E58/D58 -> 38.836661 | D58: 551 | E58: 21399
B59: Мини-наклейки | C59: =E59/D59 -> 19.970909 | D59: =1650/3 -> 550 | E59: 10984
B60: Бонд-наклейки | C60: =E60/D60 -> 15.978182 | D60: 550 | E60: 8788
B61: Медальоны 80мм | C61: =E61/D61 -> 39.319588 | D61: 194 | E61: 7628
B62: Медальоны 100мм | C62: =E62/D62 -> 42.610442 | D62: 249 | E62: 10610
B63: Медальоны 120мм | C63: =E63/D63 -> 88.801802 | D63: 111 | E63: 9857
B64: Дневник | C64: =E64/D64 -> 212.72727 | D64: 550 | E64: 117000
A65: Логистика | B65: Логистика: Поставщик → Я | C65: =4400+3240+38+1100+224+500+4000 -> 13502
A66: Расходы маркетплейса | C66: =SUM(C67:E71) -> 0
A67: Комиссия OZON, 20% от стоимости | C67: 0
A68: Эквайринг всключен в комиссию OZON | C68: 0
A69: Логистика | B69: Логистика: Я → OZON | C69: 0
B70: Логистика: внутри Ozon | C70: 0
B71: Логистика: Ozon → User, Last Mile | C71: 0
B72: Нелокальная наценка | C72: 0
A73: Маркетинговые расходы | C73: 0
A74: Ozon | B74: Продвижение карточки | E74: 0
A75: Операционные расходы | C75: =SUM(C76:E88) -> 145360
A76: Админ часть | B76: Оплата счета в Точке (месяц) | C76: 2000
B77: Бух услуги (год) | C77: =16900 -> 16900
B78: ЭДО (год) | C78: 2900
B79: Оплата Домена (год) | C79: 5412
B80: Оплата почтового адреса (год) | C80: 4500
B81: Оплата ИИшки (месяц) | C81: 7500
B82: Услуги юриста | C82: 0
A83: Ops часть | B83: Закупка инструментов хранения-сборки (3 года) | C83: =373+180+1589+257+163+511+531+2946+5061+5660+182+402+860+1544+1267+216+155 -> 21897
B84: Пробы в типографии (год) | C84: =6500+3435+1353 -> 11288
B85: Тесты упаковок/материалов (год) | C85: =5182+1014+753+1305+1740+409+860+722 -> 11985
B86: Закупка ЭЦП (3 года) | C86: 2127
B87: Оплата патента (10 лет) | C87: =18000+31500 -> 49500
B88: Закупка техники (3 года) | C88: =5926+3425 -> 9351
A89: Возвраты / брак | C89: 0
A90: EAT | C90: =SUM(C91:E92) -> 0
A91: Взносы в Соц. фонд
A92: Налог УСН "Доходы минус расходы" 15% | C92: 0
A93: RE | C93: =C94 -> 0
A94: Дивиденты Насте | C94: 0

Sheet Ценообразование
D1: Антуриум | E1: Аглаонема | F1: Эпипремнум | G1: Спатифиллум | H1: Замиакулькас | I1: Монстера | J1: Фикус
B2: 1,2 литра
A3: Цена | D3: 1890
A4: Расходы маркетплейса | B4: Комиссия Ozon | C4: 0.24 | D4: =D3*C4 -> 453.6
B5: Эквайринг | C5: 0.01 | D5: =D3*C5 -> 18.9
B6: Логистика | C6: Логистика: Я → OZON | D6: 30
C7: Поштучная приемка | D7: 8
C8: Логистика: внутри Ozon | D8: 80
C9: Логистика: Ozon → User, Last Mile | D9: 25
C10: Нелокальная наценка | D10: 0
C11: Возвраты (8%) | D11: =225*0.08 -> 18
A12: Маркетинговые расходы | B12: OZON | C12: Продвижение карточки | D12: =155000/1800 -> 86.111111
A13: Операционные расходы | B13: Админ часть | C13: Оплата счета в Точке | D13: ='P&L факт'!C76*9/1800 -> 10
C14: Бух услуги | D14: ='P&L факт'!C77/1800 -> 9.3888889
C15: ЭДО | D15: ='P&L факт'!C78/1800 -> 1.6111111
C16: Оплата Домена | D16: ='P&L факт'!C79/1800 -> 3.0066667
C17: Оплата почтового адреса | D17: ='P&L факт'!C80/1800 -> 2.5
C18: Оплата ИИшки | D18: ='P&L факт'!C81*12/1800 -> 50
C19: Услуги юриста | D19: ='P&L факт'!C82/1800 -> 0
B20: Ops часть | C20: Все вместе | D20: =(('P&L факт'!C83+'P&L факт'!C86+'P&L факт'!C88)/3/12+('P&L факт'!C84+'P&L факт'!C85)/12+'P&L факт'!C87/10/12)/500 -> 6.558
A21: Сумма Маркетинг+Маркетплейс+Операционка | D21: =SUM(D4:H20) -> 802.67578
A22: Себестоимость продукта | D22: ='Себестоимость продукта'!C3 -> 595.26208 | E22: ='Себестоимость продукта'!D3 -> 577.67948 | F22: ='Себестоимость продукта'!E3 -> 583.83411 | G22: ='Себестоимость продукта'!F3 -> 579.26651 | H22: ='Себестоимость продукта'!G3 -> 589.47948
A23: Чистая прибыль в % | D23: =D24/D3 -> 0.26035034 | E23: =E24/D3 -> 0.2696533 | F23: =F24/D3 -> 0.26639688 | G23: =G24/D3 -> 0.26881361 | H23: =H24/D3 -> 0.26340992
A24: Чистая прибыль в рублях | D24: =D3-D21-D22 -> 492.06214 | E24: =D3-D21-E22 -> 509.64474 | F24: =D3-D21-F22 -> 503.49011 | G24: =D3-D21-G22 -> 508.05771 | H24: =D3-D21-H22 -> 497.84474 | L24: =SUM(D24:H24)/5*175 -> 87888.481
B25: 2,2 литра
A26: Цена | D26: 2190
A27: Расходы маркетплейса | B27: Комиссия Ozon | C27: 0.24 | D27: =D26*C27 -> 525.6
B28: Эквайринг | C28: 0.01 | D28: =D26*C28 -> 21.9
B29: Логистика | C29: Логистика: Я → OZON | D29: 40
C30: Поштучная приемка | D30: 10
C31: Логистика: внутри Ozon | D31: 110
C32: Логистика: Ozon → User, Last Mile | D32: 25
C33: Нелокальная наценка | D33: 0
C34: Возвраты (8%) | D34: =305*0.08 -> 24.4
A35: Маркетинговые расходы | B35: OZON | C35: Продвижение карточки | D35: =155000/1800 -> 86.111111
A36: Операционные расходы | B36: Админ часть | C36: Оплата счета в Точке | D36: ='P&L факт'!C76*10/1800 -> 11.111111
C37: Бух услуги | D37: ='P&L факт'!C77/1800 -> 9.3888889
C38: ЭДО | D38: ='P&L факт'!C78/1800 -> 1.6111111
C39: Оплата Домена | D39: ='P&L факт'!C79/1800 -> 3.0066667
C40: Оплата ИИшки | D40: ='P&L факт'!C81*12/1800 -> 50
C41: Услуги юриста | D41: ='P&L факт'!C82/1800 -> 0
B42: Ops часть | C42: Все вместе | D42: =(('P&L факт'!C83+'P&L факт'!C86+'P&L факт'!C88)/3/12+('P&L факт'!C84+'P&L факт'!C85)/12+'P&L факт'!C87/10/12)/500 -> 6.558
A43: Сумма Маркетинг+Маркетплейс+Операционка | D43: =SUM(D27:J42) -> 924.68689
A44: Себестоимость продукта | D44: ='Себестоимость продукта'!C26 -> 708.63888 | E44: ='Себестоимость продукта'!D26 -> 676.40411 | F44: ='Себестоимость продукта'!E26 -> 687.6876 | G44: ='Себестоимость продукта'!F26 -> 679.31366 | H44: ='Себестоимость продукта'!G26 -> 698.03745 | I44: ='Себестоимость продукта'!H26 -> 707.25491 | J44: ='Себестоимость продукта'!I26 -> 690.28418
A45: Чистая прибыль в % | D45: =D46/D26 -> 0.25418915 | E45: =E46/D26 -> 0.26890822 | F45: =F46/D26 -> 0.26375594 | G45: =G46/D26 -> 0.26757966 | H45: =H46/D26 -> 0.26757966 | I45: =I46/D26 -> 0.2548211 | J45: =J46/D26 -> 0.26257029
A46: Чистая прибыль в рублях | D46: =D26-D43-D44 -> 556.67423 | E46: =D26-D43-E44 -> 588.909 | F46: =D26-D43-F44 -> 577.62551 | G46: =D26-D43-G44 -> 585.99945 | H46: =D26-D43-G44 -> 585.99945 | I46: =D26-D43-I44 -> 558.0582 | J46: =D26-D43-J44 -> 575.02893 | L46: =SUM(D46:J46)/7*225 -> 129480.9
B47: 3,5 литра
A48: Цена | G48: 2590
A49: Расходы маркетплейса | B49: Комиссия Ozon | C49: 0.24 | G49: =G48*C49 -> 621.6
B50: Эквайринг | C50: 0.01 | G50: =G48*C50 -> 25.9
B51: Логистика | C51: Логистика: Я → OZON | G51: 50
C52: Поштучная приемка | G52: 11
C53: Логистика: внутри Ozon | G53: 120
C54: Логистика: Ozon → User, Last Mile | G54: 25
C55: Нелокальная наценка | G55: 0
C56: Возвраты (8%) | G56: =355*0.08 -> 28.4
A57: Маркетинговые расходы | B57: OZON | C57: Продвижение карточки | G57: =155000/1800 -> 86.111111
A58: Операционные расходы | B58: Админ часть | C58: Оплата счета в Точке | G58: ='P&L факт'!C76*10/1800 -> 11.111111
C59: Бух услуги | G59: ='P&L факт'!C77/1800 -> 9.3888889
C60: ЭДО | G60: ='P&L факт'!C78/1800 -> 1.6111111
C61: Оплата Домена | G61: ='P&L факт'!C79/1800 -> 3.0066667
C62: Оплата ИИшки | G62: ='P&L факт'!C81*12/1800 -> 50
C63: Услуги юриста | G63: ='P&L факт'!C82/1800 -> 0
B64: Ops часть | C64: Все вместе | G64: =(('P&L факт'!C83+'P&L факт'!C86+'P&L факт'!C88)/3/12+('P&L факт'!C84+'P&L факт'!C85)/12+'P&L факт'!C87/10/12)/500 -> 6.558
A65: Сумма Маркетинг+Маркетплейс+Операционка | G65: =SUM(G49:J64) -> 1049.6869
A66: Себестоимость продукта | G66: ='Себестоимость продукта'!F49 -> 849.34959 | H66: ='Себестоимость продукта'!G49 -> 879.13743 | I66: ='Себестоимость продукта'!H49 -> 893.80156 | J66: ='Себестоимость продукта'!I49 -> 866.80268
A67: Чистая прибыль в % | G67: =G68/G48 -> 0.26678128 | H67: =H68/G48 -> 0.25528019 | I67: =I68/G48 -> 0.24961836 | J67: =J68/G48 -> 0.26004264
A68: Чистая прибыль в рублях | G68: =G48-G65-G66 -> 690.96352 | H68: =G48-G65-H66 -> 661.17568 | I68: =G48-G65-I66 -> 646.51155 | J68: =G48-G65-J66 -> 673.51044 | L68: =SUM(G68:J68)/4*100 -> 66804.03

Sheet Себестоимость продукта
C1: Антуриум | D1: Аглаонема | E1: Эпипремнум | F1: Спатифиллум | G1: Замиакулькас | H1: Монстера | I1: Фикус
A2: 1.2
A3: Себестоимость продукта | C3: =SUM(C5:I24)+C4 -> 595.26208 | D3: =SUM(C5:I24)+D4 -> 577.67948 | E3: =SUM(C5:I24)+E4 -> 583.83411 | F3: =SUM(C5:I24)+F4 -> 579.26651 | G3: =SUM(C5:I24)+G4 -> 589.47948
A4: Почвосмесь | C4: ='Конструктор грунта'!P47 -> 107.16728 | D4: ='Конструктор грунта'!P44 -> 89.584684 | E4: ='Конструктор грунта'!P50 -> 95.739315 | F4: ='Конструктор грунта'!P48 -> 91.171711 | G4: ='Конструктор грунта'!P46 -> 101.38468
A5: Допы | B5: Перчатки, М | C5: ='P&L факт'!C38 -> 10.061818
B6: Корневин, 5г | C6: ='P&L факт'!C39 -> 23.414815
A7: Упаковка | B7: Квадропак П 135+65х225 | C7: ='P&L факт'!C41 -> 15.57
B8: Квадропак Ц 110+60x190 | C8: ='P&L факт'!C40 -> 12.05
B9: Коробка 200х200х100 | C9: ='P&L факт'!C45 -> 39.3
B10: Конверт | C10: ='P&L факт'!C48 -> 12.231034
B11: Сотовая крафт-бумага | C11: ='P&L факт'!C49*0.5 -> 14.747619
B12: Скотч-стикер круглый | C12: ='P&L факт'!C50*2 -> 0.86
B13: Курьерский пакет 240х320 | C13: ='P&L факт'!C51 -> 2.7
B14: Стикер для штрихкода mini | C14: ='P&L факт'!C54 -> 0.1835
B15: Коробка для отгрузки | C15: ='P&L факт'!C55/24 -> 3.0445833
B16: Стикер для штрихкода maxi | C16: ='P&L факт'!C56/24 -> 0.023055556
B17: Скотч | C17: =124/180*2.5/24 -> 0.071759259
A18: Бренд | B18: Велком-листовка | C18: ='P&L факт'!C58 -> 38.836661
B19: Мини-наклейки | C19: ='P&L факт'!C59 -> 19.970909
B20: Бонд-наклейки | C20: ='P&L факт'!C60 -> 15.978182
B21: Медальоны 80мм | C21: ='P&L факт'!C61 -> 39.319588
B22: Дневник | C22: ='P&L факт'!C64 -> 212.72727
A23: Операционка | B23: Логистика: → Я | C23: ='P&L факт'!C65/500 -> 27.004
B24: Сортировка (мои руки) | C24: 0
A25: 2.2
A26: Себестоимость продукта | C26: =SUM(C28:I47)+C27 -> 708.63888 | D26: =SUM(C28:I47)+D27 -> 676.40411 | E26: =SUM(C28:I47)+E27 -> 687.6876 | F26: =SUM(C28:I47)+F27 -> 679.31366 | G26: =SUM(C28:I47)+G27 -> 698.03745 | H26: =SUM(C28:I47)+H27 -> 707.25491 | I26: =SUM(C28:I47)+I27 -> 690.28418
A27: Почвосмесь | C27: ='Конструктор грунта'!R47 -> 196.47335 | D27: ='Конструктор грунта'!R44 -> 164.23859 | E27: ='Конструктор грунта'!R50 -> 175.52208 | F27: ='Конструктор грунта'!R48 -> 167.14814 | G27: ='Конструктор грунта'!R46 -> 185.87192 | H27: ='Конструктор грунта'!R45 -> 195.08938 | I27: ='Конструктор грунта'!R63 -> 178.11865
A28: Допы | B28: Перчатки, М | C28: ='P&L факт'!C38 -> 10.061818
B29: Корневин, 5г | C29: ='P&L факт'!C39 -> 23.414815
A30: Упаковка | B30: Квадропак П 150+90х250 | C30: ='P&L факт'!C43 -> 19.34
B31: Квадропак Ц 110+60x190 | C31: ='P&L факт'!C40 -> 12.05
B32: Коробка 250×250×100 | C32: ='P&L факт'!C46 -> 45.8
B33: Конверт | C33: ='P&L факт'!C48 -> 12.231034
B34: Сотовая крафт-бумага | C34: ='P&L факт'!C49*0.7 -> 20.646667
B35: Скотч-стикер круглый | C35: ='P&L факт'!C50*2 -> 0.86
B36: Курьерский пакет 300х400 | C36: ='P&L факт'!C52 -> 3.5
B37: Стикер для штрихкода mini | C37: ='P&L факт'!C54 -> 0.1835
B38: Коробка для отгрузки | C38: ='P&L факт'!C55/11 -> 6.6427273
B39: Стикер для штрихкода maxi | C39: ='P&L факт'!C56/6 -> 0.092222222
B40: Скотч | C40: =124/180*2.5/8 -> 0.21527778
A41: Бренд | B41: Велком-листовка | C41: ='P&L факт'!C58 -> 38.836661
B42: Мини-наклейки | C42: ='P&L факт'!C59 -> 19.970909
B43: Бонд-наклейки | C43: ='P&L факт'!C60 -> 15.978182
B44: Медальоны 100мм | C44: ='P&L факт'!C62 -> 42.610442
B45: Дневник | C45: ='P&L факт'!C64 -> 212.72727
A46: Операционка | B46: Логистика: → Я | C46: ='P&L факт'!C65/500 -> 27.004
B47: Сортировка (мои руки) | C47: 0
A48: 3.5
A49: Себестоимость продукта | F49: =SUM(C51:I69)+F50 -> 849.34959 | G49: =SUM(C51:I69)+G50 -> 879.13743 | H49: =SUM(C51:I69)+H50 -> 893.80156 | I49: =SUM(C51:I69)+I50 -> 866.80268
A50: Почвосмесь | F50: ='Конструктор грунта'!T48 -> 265.91749 | G50: ='Конструктор грунта'!T46 -> 295.70533 | H50: ='Конструктор грунта'!T45 -> 310.36947 | I50: ='Конструктор грунта'!T63 -> 283.37058
A51: Допы | B51: Перчатки, М | C51: ='P&L факт'!C38 -> 10.061818
B52: Корневин, 5г | C52: ='P&L факт'!C39 -> 23.414815
A53: Упаковка | B53: Квадропак П 150+90х345 | C53: ='P&L факт'!C44 -> 22.86
B54: Квадропак Ц 135+65х225 | C54: ='P&L факт'!C41 -> 15.57
B55: Коробка 320×320×100 | C55: ='P&L факт'!C47 -> 56.46
B56: Конверт | C56: ='P&L факт'!C48 -> 12.231034
B57: Сотовая крафт-бумага | C57: ='P&L факт'!C49*0.9 -> 26.545714
B58: Скотч-стикер круглый | C58: ='P&L факт'!C50*2 -> 0.86
B59: Курьерский пакет 300х400 | C59: ='P&L факт'!C52 -> 3.5
B60: Стикер для штрихкода mini | C60: ='P&L факт'!C54 -> 0.1835
B61: Коробка для отгрузки | C61: ='P&L факт'!C55/9 -> 8.1188889
B62: Стикер для штрихкода maxi | C62: ='P&L факт'!C56/6 -> 0.092222222
B63: Скотч | C63: =124/180*2.5/8 -> 0.21527778
A64: Бренд | B64: Велком-листовка | C64: ='P&L факт'!C58 -> 38.836661
B65: Мини-наклейки | C65: ='P&L факт'!C59 -> 19.970909
B66: Бонд-наклейки | C66: ='P&L факт'!C60 -> 15.978182
B67: Медальоны 120мм | C67: ='P&L факт'!C63 -> 88.801802
B68: Дневник | C68: ='P&L факт'!C64 -> 212.72727
A69: Операционка | B69: Логистика: → Я | C69: ='P&L факт'!C65/500 -> 27.004
B70: Сортировка (мои руки) | C70: 0

Sheet Конструктор грунта
A1: процентное соотношение ингридиента в почвосмеси
A2: Растение | B2: Торф нейтральный | C2: Торф кислый | D2: Кора сосновая | E2: Кокосовый субстрат и чипсы | F2: Диатомит | G2: Цеолит вулканический | H2: Пеностекло | I2: Мох сфагнум | J2: Уголь | K2: Песок | L2: Биогумус | N2: Сумма
A3: Сциндапсус | B3: 0.3 | D3: 0.15 | E3: 0.1 | F3: 0.05 | G3: 0.1 | H3: 0.05 | I3: 0.1 | J3: 0.1 | L3: 0.05 | N3: =SUM(B3:L3) -> 1
A4: Алоказия | B4: 0.3 | D4: 0.1 | E4: 0.1 | F4: 0.1 | G4: 0.1 | H4: 0.05 | J4: 0.1 | K4: 0.1 | L4: 0.05 | N4: =SUM(B4:L4) -> 1
A5: Аглаонема | B5: 0.25 | C5: 0.1 | D5: 0.1 | E5: 0.1 | F5: 0.05 | G5: 0.1 | H5: 0.05 | J5: 0.1 | K5: 0.1 | L5: 0.05 | N5: =SUM(B5:L5) -> 1
A6: Монстера | B6: 0.2 | D6: 0.15 | E6: 0.1 | F6: 0.05 | G6: 0.15 | H6: 0.05 | I6: 0.1 | J6: 0.1 | K6: 0.05 | L6: 0.05 | N6: =SUM(B6:L6) -> 1
A7: Замиокулькас | B7: 0.25 | E7: 0.1 | F7: 0.1 | G7: 0.15 | H7: 0.15 | J7: 0.1 | K7: 0.1 | L7: 0.05 | N7: =SUM(B7:L7) -> 1
A8: Антуриум | B8: 0.1 | D8: 0.2 | E8: 0.2 | F8: 0.05 | G8: 0.1 | H8: 0.05 | I8: 0.1 | J8: 0.1 | K8: 0.05 | L8: 0.05 | N8: =SUM(B8:L8) -> 1
A9: Спатифиллум | B9: 0.25 | C9: 0.1 | D9: 0.1 | E9: 0.1 | F9: 0.05 | G9: 0.1 | H9: 0.05 | I9: 0.05 | J9: 0.1 | K9: 0.05 | L9: 0.05 | N9: =SUM(B9:L9) -> 1
A10: Филодендрон | B10: 0.2 | D10: 0.15 | E10: 0.1 | F10: 0.05 | G10: 0.15 | H10: 0.05 | I10: 0.1 | J10: 0.1 | K10: 0.05 | L10: 0.05 | N10: =SUM(B10:L10) -> 1
A11: Эпипремнум | B11: 0.3 | D11: 0.15 | E11: 0.1 | F11: 0.05 | G11: 0.1 | H11: 0.05 | I11: 0.1 | J11: 0.1 | L11: 0.05 | N11: =SUM(B11:L11) -> 1
A12: Хойя | B12: 0.25 | C12: 0.05 | D12: 0.1 | E12: 0.1 | F12: 0.1 | G12: 0.1 | H12: 0.05 | J12: 0.1 | K12: 0.1 | L12: 0.05 | N12: =SUM(B12:L12) -> 1
A13: Церопегия | B13: 0.4 | E13: 0.075 | F13: 0.1 | G13: 0.15 | H13: 0.05 | J13: 0.1 | K13: 0.075 | L13: 0.05 | N13: =SUM(B13:L13) -> 1
A14: Калатея | B14: 0.3 | C14: 0.1 | D14: 0.05 | E14: 0.1 | G14: 0.1 | H14: 0.05 | I14: 0.15 | J14: 0.1 | L14: 0.05 | N14: =SUM(B14:L14) -> 1
B15: 0.3 | C15: 0.1 | D15: 0.1 | E15: 0.15 | G15: 0.1 | H15: 0.05 | I15: 0.05 | J15: 0.1 | L15: 0.05 | N15: =SUM(B15:L15) -> 1
A16: Аспидистра | B16: 0.35 | D16: 0.05 | E16: 0.1 | F16: 0.1 | G16: 0.1 | H16: 0.05 | J16: 0.1 | K16: 0.1 | L16: 0.05 | N16: =SUM(B16:L16) -> 1
A17: Сансевиерия | B17: 0.25 | E17: 0.1 | F17: 0.1 | G17: 0.15 | H17: 0.15 | J17: 0.1 | K17: 0.1 | L17: 0.05 | N17: =SUM(B17:L17) -> 1
A18: Хлорофитум | B18: 0.35 | D18: 0.05 | E18: 0.1 | F18: 0.1 | G18: 0.1 | H18: 0.05 | I18: 0.1 | J18: 0.1 | L18: 0.05 | N18: =SUM(B18:L18) -> 1
A19: Драцена | B19: 0.35 | D19: 0.05 | E19: 0.1 | F19: 0.1 | G19: 0.15 | H19: 0.05 | J19: 0.1 | K19: 0.05 | L19: 0.05 | N19: =SUM(B19:L19) -> 1
A20: Стрелиция | B20: 0.3 | C20: 0.1 | E20: 0.1 | F20: 0.1 | G20: 0.15 | H20: 0.05 | J20: 0.1 | K20: 0.05 | L20: 0.05 | N20: =SUM(B20:L20) -> 1
A21: Юкка | B21: 0.35 | F21: 0.1 | G21: 0.15 | H21: 0.1 | J21: 0.1 | K21: 0.15 | L21: 0.05 | N21: =SUM(B21:L21) -> 1
A22: Хамедорея | B22: 0.35 | D22: 0.05 | E22: 0.05 | F22: 0.1 | G22: 0.15 | H22: 0.05 | J22: 0.1 | K22: 0.1 | L22: 0.05 | N22: =SUM(B22:L22) -> 1
A23: Ховея | B23: 0.35 | D23: 0.05 | E23: 0.05 | F23: 0.1 | G23: 0.15 | H23: 0.05 | J23: 0.1 | K23: 0.1 | L23: 0.05 | N23: =SUM(B23:L23) -> 1
A24: Фикусы | B24: 0.3 | D24: 0.1 | E24: 0.1 | F24: 0.1 | G24: 0.15 | H24: 0.05 | J24: 0.1 | K24: 0.05 | L24: 0.05 | N24: =SUM(B24:L24) -> 1
A25: Шеффлера | B25: 0.3 | C25: 0.1 | D25: 0.05 | E25: 0.1 | F25: 0.05 | G25: 0.1 | H25: 0.05 | J25: 0.1 | K25: 0.1 | L25: 0.05 | N25: =SUM(B25:L25) -> 1
B26: 0.3 | F26: 0.15 | G26: 0.15 | H26: 0.1 | J26: 0.1 | K26: 0.2 | N26: =SUM(B26:L26) -> 1
B27: 0.25 | C27: 0.1 | D27: 0.05 | E27: 0.1 | F27: 0.05 | G27: 0.1 | H27: 0.05 | J27: 0.1 | K27: 0.1 | L27: 0.1 | N27: =SUM(B27:L27) -> 1
A28: Фиалки | B28: 0.15 | C28: 0.15 | E28: 0.1 | F28: 0.05 | G28: 0.1 | H28: 0.15 | I28: 0.1 | J28: 0.05 | K28: 0.1 | L28: 0.05 | N28: =SUM(B28:L28) -> 1
A30: Нижняя граница | B30: =MIN(B3:B28) -> 0.1 | C30: =MIN(C3:C28) -> 0.05 | D30: =MIN(D3:D28) -> 0.05 | E30: =MIN(E3:E28) -> 0.05 | F30: =MIN(F3:F28) -> 0.05 | G30: =MIN(G3:G28) -> 0.1 | H30: =MIN(H3:H28) -> 0.05 | I30: =MIN(I3:I28) -> 0.05 | ... L30: =MIN(L3:L28) -> 0.05
A31: Верхняя граница | B31: =MAX(B3:B28) -> 0.4 | C31: =MAX(C3:C28) -> 0.15 | D31: =MAX(D3:D28) -> 0.2 | E31: =MAX(E3:E28) -> 0.2 | F31: =MAX(F3:F28) -> 0.15 | G31: =MAX(G3:G28) -> 0.15 | H31: =MAX(H3:H28) -> 0.15 | I31: =MAX(I3:I28) -> 0.15 | ... L31: =MAX(L3:L28) -> 0.1
A39: себестоимость литра грунта
A40: Растение | B40: Торф нейтральный | C40: Торф кислый | D40: Кора сосновая | E40: Кокосовый субстрат | F40: Диатомит | G40: Цеолит | H40: Пеностекло | I40: Мох сфагнум | J40: Уголь | K40: Песок | L40: Биогумус | M40: Дренаж | N40: Стоимость 1 литра грунта | O40: Стоимость 0,6л | P40: Стоимость 1,2л | Q40: Стоимость 1,8л | R40: Стоимость 2,2л | S40: Стоимость 3л | T40: Стоимость 3,5л | U40: Стоимость 4л | V40: Стоимость 5л | W40: Стоимость 6л
B41: 0.85 | M41: 0.25
A42: Сциндапсус | B42: ='P&L факт'!C25*B3*A41 -> 0 | C42: ='P&L факт'!C26*C3*A41 -> 0 | D42: =('P&L факт'!E34+'P&L факт'!E35)/('P&L факт'!D34+'P&L факт'!D35)*A41*D3 -> 0 | E42: ='P&L факт'!C27*E3*A41 -> 0 | F42: ='P&L факт'!C28*F3*A41 -> 0 | G42: ='P&L факт'!C29*G3*A41 -> 0 | H42: ='P&L факт'!C33*A41*H3 -> 0 | I42: =#REF!/#REF!*A41*I3 -> #REF! | J42: =#REF!/#REF!*A41*J3 -> #REF! | K42: =#REF!/#REF!*A41*K3 -> #REF! | L42: =#REF!/#REF!*A41*L3 -> #REF! | M42: =#REF!/#REF!*M41 -> #REF! | N42: =SUM(B42:M42) -> #REF! | O42: =N42*0.6 -> #REF! | P42: =N42*1.2 -> #REF! | Q42: =N42*1.8 -> #REF! | R42: =N42*2.2 -> #REF! | S42: =N42*3 -> #REF! | T42: =N42*3.5 -> #REF! | U42: =N42*4 -> #REF! | V42: =N42*5 -> #REF! | W42: =N42*6 -> #REF!
A43: Алоказия | B43: ='P&L факт'!C25*B4*A41 -> 0 | C43: ='P&L факт'!C26*C4*A41 -> 0 | D43: =('P&L факт'!E34+'P&L факт'!E35)/('P&L факт'!D34+'P&L факт'!D35)*A41*D4 -> 0 | E43: ='P&L факт'!C27*E4*A41 -> 0 | F43: ='P&L факт'!C28*F4*A41 -> 0 | G43: ='P&L факт'!C29*G4*A41 -> 0 | H43: ='P&L факт'!C33*A41*H4 -> 0 | I43: =#REF!/#REF!*A41*I4 -> #REF! | J43: =#REF!/#REF!*A41*J4 -> #REF! | K43: =#REF!/#REF!*A41*K4 -> #REF! | L43: =#REF!/#REF!*A41*L4 -> #REF! | M43: =#REF!/#REF!*M41 -> #REF! | N43: =SUM(B43:M43) -> #REF! | O43: =N43*0.6 -> #REF! | P43: =N43*1.2 -> #REF! | Q43: =N43*1.8 -> #REF! | R43: =N43*2.2 -> #REF! | S43: =N43*3 -> #REF! | T43: =N43*3.5 -> #REF! | U43: =N43*4 -> #REF! | V43: =N43*5 -> #REF! | W43: =N43*6 -> #REF!
A44: Аглаонема | B44: ='P&L факт'!C25*B5*B41 -> 3.9474 | C44: ='P&L факт'!C26*C5*B41 -> 1.7056667 | D44: ='P&L факт'!C34*B41*D5 -> 6.8 | E44: ='P&L факт'!C27*E5*B41 -> 5.695 | F44: ='P&L факт'!C28*F5*B41 -> 3.9245714 | G44: ='P&L факт'!C29*G5*B41 -> 13.773923 | H44: ='P&L факт'!C33*B41*H5 -> 3.7637338 | I44: ='P&L факт'!C30*B41*I5 -> 0 | J44: ='P&L факт'!C31*B41*J5 -> 9.5461538 | K44: ='P&L факт'!C36*B41*K5 -> 7.1724545 | L44: ='P&L факт'!C32*B41*L5 -> 3.825 | M44: ='P&L факт'!C37*M41 -> 14.5 | N44: =SUM(B44:M44) -> 74.653903 | O44: =N44*0.6 -> 44.792342 | P44: =N44*1.2 -> 89.584684 | Q44: =N44*1.8 -> 134.37703 | R44: =N44*2.2 -> 164.23859 | S44: =N44*3 -> 223.96171 | T44: =N44*3.5 -> 261.28866 | U44: =N44*4 -> 298.61561 | V44: =N44*5 -> 373.26952 | W44: =N44*6 -> 447.92342
A45: Монстера | B45: ='P&L факт'!C25*B6*B41 -> 3.15792 | C45: ='P&L факт'!C26*C6*B41 -> 0 | D45: ='P&L факт'!C34*B41*D6 -> 10.2 | E45: ='P&L факт'!C27*E6*B41 -> 5.695 | F45: ='P&L факт'!C28*F6*B41 -> 3.9245714 | G45: ='P&L факт'!C29*G6*B41 -> 20.660885 | H45: ='P&L факт'!C33*B41*H6 -> 3.7637338 | I45: ='P&L факт'!C30*B41*I6 -> 9.8175 | J45: ='P&L факт'!C31*B41*J6 -> 9.5461538 | K45: ='P&L факт'!C36*B41*K6 -> 3.5862273 | L45: ='P&L факт'!C32*B41*L6 -> 3.825 | M45: ='P&L факт'!C37*M41 -> 14.5 | N45: =SUM(B45:M45) -> 88.676991 | O45: =N45*0.6 -> 53.206195 | P45: =N45*1.2 -> 106.41239 | Q45: =N45*1.8 -> 159.61858 | R45: =N45*2.2 -> 195.08938 | S45: =N45*3 -> 266.03097 | T45: =N45*3.5 -> 310.36947 | U45: =N45*4 -> 354.70796 | V45: =N45*5 -> 443.38495 | W45: =N45*6 -> 532.06195
A46: Замиокулькас | B46: ='P&L факт'!C25*B7*B41 -> 3.9474 | C46: ='P&L факт'!C26*C7*B41 -> 0 | D46: ='P&L факт'!C34*B41*D7 -> 0 | E46: ='P&L факт'!C27*E7*B41 -> 5.695 | F46: ='P&L факт'!C28*F7*B41 -> 7.8491429 | G46: ='P&L факт'!C29*G7*B41 -> 20.660885 | H46: ='P&L факт'!C33*B41*H7 -> 11.291201 | I46: ='P&L факт'!C30*B41*I7 -> 0 | J46: ='P&L факт'!C31*B41*J7 -> 9.5461538 | K46: ='P&L факт'!C36*B41*K7 -> 7.1724545 | L46: ='P&L факт'!C32*B41*L7 -> 3.825 | M46: ='P&L факт'!C37*M41 -> 14.5 | N46: =SUM(B46:M46) -> 84.487237 | O46: =N46*0.6 -> 50.692342 | P46: =N46*1.2 -> 101.38468 | Q46: =N46*1.8 -> 152.07703 | R46: =N46*2.2 -> 185.87192 | S46: =N46*3 -> 253.46171 | T46: =N46*3.5 -> 295.70533 | U46: =N46*4 -> 337.94895 | V46: =N46*5 -> 422.43619 | W46: =N46*6 -> 506.92342
A47: Антуриум | B47: ='P&L факт'!C25*B8*B41 -> 1.57896 | C47: ='P&L факт'!C26*C8*B41 -> 0 | D47: ='P&L факт'!C34*B41*D8 -> 13.6 | E47: ='P&L факт'!C27*E8*B41 -> 11.39 | F47: ='P&L факт'!C28*F8*B41 -> 3.9245714 | G47: ='P&L факт'!C29*G8*B41 -> 13.773923 | H47: ='P&L факт'!C33*B41*H8 -> 3.7637338 | I47: ='P&L факт'!C30*B41*I8 -> 9.8175 | J47: ='P&L факт'!C31*B41*J8 -> 9.5461538 | K47: ='P&L факт'!C36*B41*K8 -> 3.5862273 | L47: ='P&L факт'!C32*B41*L8 -> 3.825 | M47: ='P&L факт'!C37*M41 -> 14.5 | N47: =SUM(B47:M47) -> 89.306069 | O47: =N47*0.6 -> 53.583642 | P47: =N47*1.2 -> 107.16728 | Q47: =N47*1.8 -> 160.75092 | R47: =N47*2.2 -> 196.47335 | S47: =N47*3 -> 267.91821 | T47: =N47*3.5 -> 312.57124 | U47: =N47*4 -> 357.22428 | V47: =N47*5 -> 446.53035 | W47: =N47*6 -> 535.83642
A48: Спатифиллум | B48: ='P&L факт'!C25*B9*B41 -> 3.9474 | C48: ='P&L факт'!C26*C9*B41 -> 1.7056667 | D48: ='P&L факт'!C34*B41*D9 -> 6.8 | E48: ='P&L факт'!C27*E9*B41 -> 5.695 | F48: ='P&L факт'!C28*F9*B41 -> 3.9245714 | G48: ='P&L факт'!C29*G9*B41 -> 13.773923 | H48: ='P&L факт'!C33*B41*H9 -> 3.7637338 | I48: ='P&L факт'!C30*B41*I9 -> 4.90875 | J48: ='P&L факт'!C31*B41*J9 -> 9.5461538 | K48: ='P&L факт'!C36*B41*K9 -> 3.5862273 | L48: ='P&L факт'!C32*B41*L9 -> 3.825 | M48: ='P&L факт'!C37*M41 -> 14.5 | N48: =SUM(B48:M48) -> 75.976426 | O48: =N48*0.6 -> 45.585856 | P48: =N48*1.2 -> 91.171711 | Q48: =N48*1.8 -> 136.75757 | R48: =N48*2.2 -> 167.14814 | S48: =N48*3 -> 227.92928 | T48: =N48*3.5 -> 265.91749 | U48: =N48*4 -> 303.9057 | V48: =N48*5 -> 379.88213 | W48: =N48*6 -> 455.85856
A49: Филодендрон | B49: ='P&L факт'!C25*B10*A41 -> 0 | C49: ='P&L факт'!C26*C10*A41 -> 0 | D49: =('P&L факт'!E34+'P&L факт'!E35)/('P&L факт'!D34+'P&L факт'!D35)*A41*D10 -> 0 | E49: ='P&L факт'!C27*E10*A41 -> 0 | F49: ='P&L факт'!C28*F10*A41 -> 0 | G49: ='P&L факт'!C29*G10*A41 -> 0 | H49: ='P&L факт'!C33*A41*H10 -> 0 | I49: =#REF!/#REF!*A41*I10 -> #REF! | J49: =#REF!/#REF!*A41*J10 -> #REF! | K49: =#REF!/#REF!*A41*K10 -> #REF! | L49: =#REF!/#REF!*A41*L10 -> #REF! | M49: =#REF!/#REF!*M41 -> #REF! | N49: =SUM(B49:M49) -> #REF! | O49: =N49*0.6 -> #REF! | P49: =N49*1.2 -> #REF! | Q49: =N49*1.8 -> #REF! | R49: =N49*2.2 -> #REF! | S49: =N49*3 -> #REF! | T49: =N49*3.5 -> #REF! | U49: =N49*4 -> #REF! | V49: =N49*5 -> #REF! | W49: =N49*6 -> #REF!
A50: Эпипремнум | B50: ='P&L факт'!C25*B11*B41 -> 4.73688 | C50: ='P&L факт'!C26*C11*B41 -> 0 | D50: ='P&L факт'!C34*B41*D11 -> 10.2 | E50: ='P&L факт'!C27*E11*B41 -> 5.695 | F50: ='P&L факт'!C28*F11*B41 -> 3.9245714 | G50: ='P&L факт'!C29*G11*B41 -> 13.773923 | H50: ='P&L факт'!C33*B41*H11 -> 3.7637338 | I50: ='P&L факт'!C30*B41*I11 -> 9.8175 | J50: ='P&L факт'!C31*B41*J11 -> 9.5461538 | K50: ='P&L факт'!C36*B41*K11 -> 0 | L50: ='P&L факт'!C32*B41*L11 -> 3.825 | M50: ='P&L факт'!C37*M41 -> 14.5 | N50: =SUM(B50:M50) -> 79.782762 | O50: =N50*0.6 -> 47.869657 | P50: =N50*1.2 -> 95.739315 | Q50: =N50*1.8 -> 143.60897 | R50: =N50*2.2 -> 175.52208 | S50: =N50*3 -> 239.34829 | T50: =N50*3.5 -> 279.23967 | U50: =N50*4 -> 319.13105 | V50: =N50*5 -> 398.91381 | W50: =N50*6 -> 478.69657
A51: Хойя | B51: ='P&L факт'!C25*B12*A41 -> 0 | C51: ='P&L факт'!C26*C12*A41 -> 0 | D51: =('P&L факт'!E34+'P&L факт'!E35)/('P&L факт'!D34+'P&L факт'!D35)*A41*D12 -> 0 | E51: ='P&L факт'!C27*E12*A41 -> 0 | F51: ='P&L факт'!C28*F12*A41 -> 0 | G51: ='P&L факт'!C29*G12*A41 -> 0 | H51: ='P&L факт'!C33*A41*H12 -> 0 | I51: =#REF!/#REF!*A41*I12 -> #REF! | J51: =#REF!/#REF!*A41*J12 -> #REF! | K51: =#REF!/#REF!*A41*K12 -> #REF! | L51: =#REF!/#REF!*A41*L12 -> #REF! | M51: =#REF!/#REF!*M41 -> #REF! | N51: =SUM(B51:M51) -> #REF! | O51: =N51*0.6 -> #REF! | P51: =N51*1.2 -> #REF! | Q51: =N51*1.8 -> #REF! | R51: =N51*2.2 -> #REF! | S51: =N51*3 -> #REF! | T51: =N51*3.5 -> #REF! | U51: =N51*4 -> #REF! | V51: =N51*5 -> #REF! | W51: =N51*6 -> #REF!
A52: Церопегия | B52: ='P&L факт'!C25*B13*A41 -> 0 | C52: ='P&L факт'!C26*C13*A41 -> 0 | D52: =('P&L факт'!E34+'P&L факт'!E35)/('P&L факт'!D34+'P&L факт'!D35)*A41*D13 -> 0 | E52: ='P&L факт'!C27*E13*A41 -> 0 | F52: ='P&L факт'!C28*F13*A41 -> 0 | G52: ='P&L факт'!C29*G13*A41 -> 0 | H52: ='P&L факт'!C33*A41*H13 -> 0 | I52: =#REF!/#REF!*A41*I13 -> #REF! | J52: =#REF!/#REF!*A41*J13 -> #REF! | K52: =#REF!/#REF!*A41*K13 -> #REF! | L52: =#REF!/#REF!*A41*L13 -> #REF! | M52: =#REF!/#REF!*M41 -> #REF! | N52: =SUM(B52:M52) -> #REF! | O52: =N52*0.6 -> #REF! | P52: =N52*1.2 -> #REF! | Q52: =N52*1.8 -> #REF! | R52: =N52*2.2 -> #REF! | S52: =N52*3 -> #REF! | T52: =N52*3.5 -> #REF! | U52: =N52*4 -> #REF! | V52: =N52*5 -> #REF! | W52: =N52*6 -> #REF!
A53: Калатея | B53: ='P&L факт'!C25*B14*A41 -> 0 | C53: ='P&L факт'!C26*C14*A41 -> 0 | D53: =('P&L факт'!E34+'P&L факт'!E35)/('P&L факт'!D34+'P&L факт'!D35)*A41*D14 -> 0 | E53: ='P&L факт'!C27*E14*A41 -> 0 | F53: ='P&L факт'!C28*F14*A41 -> 0 | G53: ='P&L факт'!C29*G14*A41 -> 0 | H53: ='P&L факт'!C33*A41*H14 -> 0 | I53: =#REF!/#REF!*A41*I14 -> #REF! | J53: =#REF!/#REF!*A41*J14 -> #REF! | K53: =#REF!/#REF!*A41*K14 -> #REF! | L53: =#REF!/#REF!*A41*L14 -> #REF! | M53: =#REF!/#REF!*M41 -> #REF! | N53: =SUM(B53:M53) -> #REF! | O53: =N53*0.6 -> #REF! | P53: =N53*1.2 -> #REF! | Q53: =N53*1.8 -> #REF! | R53: =N53*2.2 -> #REF! | S53: =N53*3 -> #REF! | T53: =N53*3.5 -> #REF! | U53: =N53*4 -> #REF! | V53: =N53*5 -> #REF! | W53: =N53*6 -> #REF!
B54: ='P&L факт'!C25*B15*A41 -> 0 | C54: ='P&L факт'!C26*C15*A41 -> 0 | D54: =('P&L факт'!E34+'P&L факт'!E35)/('P&L факт'!D34+'P&L факт'!D35)*A41*D15 -> 0 | E54: ='P&L факт'!C27*E15*A41 -> 0 | F54: ='P&L факт'!C28*F15*A41 -> 0 | G54: ='P&L факт'!C29*G15*A41 -> 0 | H54: ='P&L факт'!C33*A41*H15 -> 0 | I54: =#REF!/#REF!*A41*I15 -> #REF! | J54: =#REF!/#REF!*A41*J15 -> #REF! | K54: =#REF!/#REF!*A41*K15 -> #REF! | L54: =#REF!/#REF!*A41*L15 -> #REF! | M54: =#REF!/#REF!*M41 -> #REF! | N54: =SUM(B54:M54) -> #REF! | O54: =N54*0.6 -> #REF! | P54: =N54*1.2 -> #REF! | Q54: =N54*1.8 -> #REF! | R54: =N54*2.2 -> #REF! | S54: =N54*3 -> #REF! | T54: =N54*3.5 -> #REF! | U54: =N54*4 -> #REF! | V54: =N54*5 -> #REF! | W54: =N54*6 -> #REF!
A55: Аспидистра | B55: ='P&L факт'!C25*B16*A41 -> 0 | C55: ='P&L факт'!C26*C16*A41 -> 0 | D55: =('P&L факт'!E34+'P&L факт'!E35)/('P&L факт'!D34+'P&L факт'!D35)*A41*D16 -> 0 | E55: ='P&L факт'!C27*E16*A41 -> 0 | F55: ='P&L факт'!C28*F16*A41 -> 0 | G55: ='P&L факт'!C29*G16*A41 -> 0 | H55: ='P&L факт'!C33*A41*H16 -> 0 | I55: =#REF!/#REF!*A41*I16 -> #REF! | J55: =#REF!/#REF!*A41*J16 -> #REF! | K55: =#REF!/#REF!*A41*K16 -> #REF! | L55: =#REF!/#REF!*A41*L16 -> #REF! | M55: =#REF!/#REF!*M41 -> #REF! | N55: =SUM(B55:M55) -> #REF! | O55: =N55*0.6 -> #REF! | P55: =N55*1.2 -> #REF! | Q55: =N55*1.8 -> #REF! | R55: =N55*2.2 -> #REF! | S55: =N55*3 -> #REF! | T55: =N55*3.5 -> #REF! | U55: =N55*4 -> #REF! | V55: =N55*5 -> #REF! | W55: =N55*6 -> #REF!
A56: Сансевиерия | B56: ='P&L факт'!C25*B17*A41 -> 0 | C56: ='P&L факт'!C26*C17*A41 -> 0 | D56: =('P&L факт'!E34+'P&L факт'!E35)/('P&L факт'!D34+'P&L факт'!D35)*A41*D17 -> 0 | E56: ='P&L факт'!C27*E17*A41 -> 0 | F56: ='P&L факт'!C28*F17*A41 -> 0 | G56: ='P&L факт'!C29*A41*G17 -> 0 | H56: ='P&L факт'!C33*A41*H17 -> 0 | I56: =#REF!/#REF!*A41*I17 -> #REF! | J56: =#REF!/#REF!*A41*J17 -> #REF! | K56: =#REF!/#REF!*A41*K17 -> #REF! | L56: =#REF!/#REF!*A41*L17 -> #REF! | M56: =#REF!/#REF!*M41 -> #REF! | N56: =SUM(B56:M56) -> #REF! | O56: =N56*0.6 -> #REF! | P56: =N56*1.2 -> #REF! | Q56: =N56*1.8 -> #REF! | R56: =N56*2.2 -> #REF! | S56: =N56*3 -> #REF! | T56: =N56*3.5 -> #REF! | U56: =N56*4 -> #REF! | V56: =N56*5 -> #REF! | W56: =N56*6 -> #REF!
A57: Хлорофитум | B57: ='P&L факт'!C25*B18*A41 -> 0 | C57: ='P&L факт'!C26*C18*A41 -> 0 | D57: =('P&L факт'!E34+'P&L факт'!E35)/('P&L факт'!D34+'P&L факт'!D35)*A41*D18 -> 0 | E57: ='P&L факт'!C27*E18*A41 -> 0 | F57: ='P&L факт'!C28*F18*A41 -> 0 | G57: ='P&L факт'!C29*A41*G18 -> 0 | H57: ='P&L факт'!C33*A41*H18 -> 0 | I57: =#REF!/#REF!*A41*I18 -> #REF! | J57: =#REF!/#REF!*A41*J18 -> #REF! | K57: =#REF!/#REF!*A41*K18 -> #REF! | L57: =#REF!/#REF!*A41*L18 -> #REF! | M57: =#REF!/#REF!*M41 -> #REF! | N57: =SUM(B57:M57) -> #REF! | O57: =N57*0.6 -> #REF! | P57: =N57*1.2 -> #REF! | Q57: =N57*1.8 -> #REF! | R57: =N57*2.2 -> #REF! | S57: =N57*3 -> #REF! | T57: =N57*3.5 -> #REF! | U57: =N57*4 -> #REF! | V57: =N57*5 -> #REF! | W57: =N57*6 -> #REF!
A58: Драцена | B58: ='P&L факт'!C25*B19*A41 -> 0 | C58: ='P&L факт'!C26*C19*A41 -> 0 | D58: =('P&L факт'!E34+'P&L факт'!E35)/('P&L факт'!D34+'P&L факт'!D35)*A41*D19 -> 0 | E58: ='P&L факт'!C27*E19*A41 -> 0 | F58: ='P&L факт'!C28*F19*A41 -> 0 | G58: ='P&L факт'!C29*A41*G19 -> 0 | H58: ='P&L факт'!C33*A41*H19 -> 0 | I58: =#REF!/#REF!*A41*I19 -> #REF! | J58: =#REF!/#REF!*A41*J19 -> #REF! | K58: =#REF!/#REF!*A41*K19 -> #REF! | L58: =#REF!/#REF!*A41*L19 -> #REF! | M58: =#REF!/#REF!*M41 -> #REF! | N58: =SUM(B58:M58) -> #REF! | O58: =N58*0.6 -> #REF! | P58: =N58*1.2 -> #REF! | Q58: =N58*1.8 -> #REF! | R58: =N58*2.2 -> #REF! | S58: =N58*3 -> #REF! | T58: =N58*3.5 -> #REF! | U58: =N58*4 -> #REF! | V58: =N58*5 -> #REF! | W58: =N58*6 -> #REF!
A59: Стрелиция | B59: ='P&L факт'!C25*B20*A41 -> 0 | C59: ='P&L факт'!C26*C20*A41 -> 0 | D59: =('P&L факт'!E34+'P&L факт'!E35)/('P&L факт'!D34+'P&L факт'!D35)*A41*D20 -> 0 | E59: ='P&L факт'!C27*E20*A41 -> 0 | F59: ='P&L факт'!C28*F20*A41 -> 0 | G59: ='P&L факт'!C29*A41*G20 -> 0 | H59: ='P&L факт'!C33*A41*H20 -> 0 | I59: =#REF!/#REF!*A41*I20 -> #REF! | J59: =#REF!/#REF!*A41*J20 -> #REF! | K59: =#REF!/#REF!*A41*K20 -> #REF! | L59: =#REF!/#REF!*A41*L20 -> #REF! | M59: =#REF!/#REF!*M41 -> #REF! | N59: =SUM(B59:M59) -> #REF! | O59: =N59*0.6 -> #REF! | P59: =N59*1.2 -> #REF! | Q59: =N59*1.8 -> #REF! | R59: =N59*2.2 -> #REF! | S59: =N59*3 -> #REF! | T59: =N59*3.5 -> #REF! | U59: =N59*4 -> #REF! | V59: =N59*5 -> #REF! | W59: =N59*6 -> #REF!
A60: Юкка | B60: ='P&L факт'!C25*B21*A41 -> 0 | C60: ='P&L факт'!C26*C21*A41 -> 0 | D60: =('P&L факт'!E34+'P&L факт'!E35)/('P&L факт'!D34+'P&L факт'!D35)*A41*D21 -> 0 | E60: ='P&L факт'!C27*E21*A41 -> 0 | F60: ='P&L факт'!C28*F21*A41 -> 0 | G60: ='P&L факт'!C29*A41*G21 -> 0 | H60: ='P&L факт'!C33*A41*H21 -> 0 | I60: =#REF!/#REF!*A41*I21 -> #REF! | J60: =#REF!/#REF!*A41*J21 -> #REF! | K60: =#REF!/#REF!*A41*K21 -> #REF! | L60: =#REF!/#REF!*A41*L21 -> #REF! | M60: =#REF!/#REF!*M41 -> #REF! | N60: =SUM(B60:M60) -> #REF! | O60: =N60*0.6 -> #REF! | P60: =N60*1.2 -> #REF! | Q60: =N60*1.8 -> #REF! | R60: =N60*2.2 -> #REF! | S60: =N60*3 -> #REF! | T60: =N60*3.5 -> #REF! | U60: =N60*4 -> #REF! | V60: =N60*5 -> #REF! | W60: =N60*6 -> #REF!
A61: Хамедорея | B61: ='P&L факт'!C25*B22*A41 -> 0 | C61: ='P&L факт'!C26*C22*A41 -> 0 | D61: =('P&L факт'!E34+'P&L факт'!E35)/('P&L факт'!D34+'P&L факт'!D35)*A41*D22 -> 0 | E61: ='P&L факт'!C27*E22*A41 -> 0 | F61: ='P&L факт'!C28*F22*A41 -> 0 | G61: ='P&L факт'!C29*A41*G22 -> 0 | H61: ='P&L факт'!C33*A41*H22 -> 0 | I61: =#REF!/#REF!*A41*I22 -> #REF! | J61: =#REF!/#REF!*A41*J22 -> #REF! | K61: =#REF!/#REF!*A41*K22 -> #REF! | L61: =#REF!/#REF!*A41*L22 -> #REF! | M61: =#REF!/#REF!*M41 -> #REF! | N61: =SUM(B61:M61) -> #REF! | O61: =N61*0.6 -> #REF! | P61: =N61*1.2 -> #REF! | Q61: =N61*1.8 -> #REF! | R61: =N61*2.2 -> #REF! | S61: =N61*3 -> #REF! | T61: =N61*3.5 -> #REF! | U61: =N61*4 -> #REF! | V61: =N61*5 -> #REF! | W61: =N61*6 -> #REF!
A62: Ховея | B62: ='P&L факт'!C25*B23*A41 -> 0 | C62: ='P&L факт'!C26*C23*A41 -> 0 | D62: =('P&L факт'!E34+'P&L факт'!E35)/('P&L факт'!D34+'P&L факт'!D35)*A41*D23 -> 0 | E62: ='P&L факт'!C27*E23*A41 -> 0 | F62: ='P&L факт'!C28*F23*A41 -> 0 | G62: ='P&L факт'!C29*A41*G23 -> 0 | H62: ='P&L факт'!C33*A41*H23 -> 0 | I62: =#REF!/#REF!*A41*I23 -> #REF! | J62: =#REF!/#REF!*A41*J23 -> #REF! | K62: =#REF!/#REF!*A41*K23 -> #REF! | L62: =#REF!/#REF!*A41*L23 -> #REF! | M62: =#REF!/#REF!*M41 -> #REF! | N62: =SUM(B62:M62) -> #REF! | O62: =N62*0.6 -> #REF! | P62: =N62*1.2 -> #REF! | Q62: =N62*1.8 -> #REF! | R62: =N62*2.2 -> #REF! | S62: =N62*3 -> #REF! | T62: =N62*3.5 -> #REF! | U62: =N62*4 -> #REF! | V62: =N62*5 -> #REF! | W62: =N62*6 -> #REF!
A63: Фикусы | B63: ='P&L факт'!C25*B24*B41 -> 4.73688 | C63: ='P&L факт'!C26*C24*B41 -> 0 | D63: ='P&L факт'!C34*B41*D24 -> 6.8 | E63: ='P&L факт'!C27*E24*B41 -> 5.695 | F63: ='P&L факт'!C28*F24*B41 -> 7.8491429 | G63: ='P&L факт'!C29*B41*G24 -> 20.660885 | H63: ='P&L факт'!C33*B41*H24 -> 3.7637338 | I63: ='P&L факт'!C30*B41*I24 -> 0 | J63: ='P&L факт'!C31*B41*J24 -> 9.5461538 | K63: ='P&L факт'!C36*B41*K24 -> 3.5862273 | L63: ='P&L факт'!C32*B41*L24 -> 3.825 | M63: ='P&L факт'!C37*M41 -> 14.5 | N63: =SUM(B63:M63) -> 80.963022 | O63: =N63*0.6 -> 48.577813 | P63: =N63*1.2 -> 97.155627 | Q63: =N63*1.8 -> 145.73344 | R63: =N63*2.2 -> 178.11865 | S63: =N63*3 -> 242.88907 | T63: =N63*3.5 -> 283.37058 | U63: =N63*4 -> 323.85209 | V63: =N63*5 -> 404.81511 | W63: =N63*6 -> 485.77813
A64: Аралиевые | B64: Шеффлера | C64: ='P&L факт'!C25*B25*A41 -> 0 | D64: ='P&L факт'!C26*C25*A41 -> 0 | E64: =('P&L факт'!E34+'P&L факт'!E35)/('P&L факт'!D34+'P&L факт'!D35)*A41*D25 -> 0 | F64: ='P&L факт'!C27*E25*A41 -> 0 | G64: ='P&L факт'!C28*F25*A41 -> 0 | H64: ='P&L факт'!C29*A41*G25 -> 0 | I64: ='P&L факт'!C33*A41*H25 -> 0 | J64: =#REF!/#REF!*A41*I25 -> #REF! | K64: =#REF!/#REF!*A41*J25 -> #REF! | L64: =#REF!/#REF!*A41*K25 -> #REF! | M64: =#REF!/#REF!*A41*L25 -> #REF! | N64: =#REF!/#REF!*M41 -> #REF! | O64: =SUM(C64:N64) -> #REF! | P64: =O64*0.6 -> #REF! | Q64: =O64*1.2 -> #REF! | R64: =O64*1.8 -> #REF! | S64: =O64*2.2 -> #REF! | T64: =O64*3 -> #REF! | U64: =O64*3.5 -> #REF! | V64: =O64*4 -> #REF! | W64: =O64*5 -> #REF! | X64: =O64*6 -> #REF!
A65: Суккуленты | C65: ='P&L факт'!C25*B26*A41 -> 0 | D65: ='P&L факт'!C26*C26*A41 -> 0 | E65: =('P&L факт'!E34+'P&L факт'!E35)/('P&L факт'!D34+'P&L факт'!D35)*A41*D26 -> 0 | F65: ='P&L факт'!C27*E26*A41 -> 0 | G65: ='P&L факт'!C28*F26*A41 -> 0 | H65: ='P&L факт'!C29*A41*G26 -> 0 | I65: ='P&L факт'!C33*A41*H26 -> 0 | J65: =#REF!/#REF!*A41*I26 -> #REF! | K65: =#REF!/#REF!*A41*J26 -> #REF! | L65: =#REF!/#REF!*A41*K26 -> #REF! | M65: =#REF!/#REF!*A41*L26 -> #REF! | N65: =#REF!/#REF!*M41 -> #REF! | O65: =SUM(C65:N65) -> #REF! | P65: =O65*0.6 -> #REF! | Q65: =O65*1.2 -> #REF! | R65: =O65*1.8 -> #REF! | S65: =O65*2.2 -> #REF! | T65: =O65*3 -> #REF! | U65: =O65*3.5 -> #REF! | V65: =O65*4 -> #REF! | W65: =O65*5 -> #REF! | X65: =O65*6 -> #REF!
A66: Цитрусовые | C66: ='P&L факт'!C25*B27*A41 -> 0 | D66: ='P&L факт'!C26*C27*A41 -> 0 | E66: =('P&L факт'!E34+'P&L факт'!E35)/('P&L факт'!D34+'P&L факт'!D35)*A41*D27 -> 0 | F66: ='P&L факт'!C27*E27*A41 -> 0 | G66: ='P&L факт'!C28*F27*A41 -> 0 | H66: ='P&L факт'!C29*A41*G27 -> 0 | I66: ='P&L факт'!C33*A41*H27 -> 0 | J66: =#REF!/#REF!*A41*I27 -> #REF! | K66: =#REF!/#REF!*A41*J27 -> #REF! | L66: =#REF!/#REF!*A41*K27 -> #REF! | M66: =#REF!/#REF!*A41*L27 -> #REF! | N66: =#REF!/#REF!*M41 -> #REF! | O66: =SUM(C66:N66) -> #REF! | P66: =O66*0.6 -> #REF! | Q66: =O66*1.2 -> #REF! | R66: =O66*1.8 -> #REF! | S66: =O66*2.2 -> #REF! | T66: =O66*3 -> #REF! | U66: =O66*3.5 -> #REF! | V66: =O66*4 -> #REF! | W66: =O66*5 -> #REF! | X66: =O66*6 -> #REF!
A67: Геснериевые | B67: Фиалки | C67: ='P&L факт'!C25*B28*A41 -> 0 | D67: ='P&L факт'!C26*C28*A41 -> 0 | E67: =('P&L факт'!E34+'P&L факт'!E35)/('P&L факт'!D34+'P&L факт'!D35)*A41*D28 -> 0 | F67: ='P&L факт'!C27*E28*A41 -> 0 | G67: ='P&L факт'!C28*F28*A41 -> 0 | H67: ='P&L факт'!C29*A41*G28 -> 0 | I67: ='P&L факт'!C33*A41*H28 -> 0 | J67: =#REF!/#REF!*A41*I28 -> #REF! | K67: =#REF!/#REF!*A41*J28 -> #REF! | L67: =#REF!/#REF!*A41*K28 -> #REF! | M67: =#REF!/#REF!*A41*L28 -> #REF! | N67: =#REF!/#REF!*M41 -> #REF! | O67: =SUM(C67:N67) -> #REF! | P67: =O67*0.6 -> #REF! | Q67: =O67*1.2 -> #REF! | R67: =O67*1.8 -> #REF! | S67: =O67*2.2 -> #REF! | T67: =O67*3 -> #REF! | U67: =O67*3.5 -> #REF! | V67: =O67*4 -> #REF! | W67: =O67*5 -> #REF! | X67: =O67*6 -> #REF!

Sheet Закупки
B2: Верхняя часть горшка
C3: Торф
C4: Наименование | D4: Ссылка 1
B5: TRUE | C5: Торф нейтральный | D5: https://www.ozon.ru/product/torf-verhovoy-ph-5-5-6-neytralizovannyy-50-l-167192648/?_bctx=CAkQwpq3Gw&at=K8tZwMk1zI7KOxRZcg7ZJ7Gtm8RKQLtn37pQru6ALMo2
B6: TRUE | C6: Торф кислый | D6: https://www.ozon.ru/product/torf-verhovoy-ph-2-5-3-5-kislyy-10-l-309908812/?at=DqtDmJZxNcEJV3gxc4yGv4NFngZ122crlDqP0Sj07j5E&from_sku=167192649&oos_search=false
C7: Добавки
C8: Наименование | D8: Ссылка 1
B9: TRUE | C9: Кокосовый субстрат | D9: https://www.ozon.ru/product/substrat-coco-mix-biobizz-50-l-790648102/
B10: TRUE | C10: Кокосовые чипсы | D10: https://bioabsolut.ru/kokosovye-chipsy-bioabsolut-dlya-rastenij.html
B11: TRUE | C11: Диатомит | D11: https://www.ozon.ru/product/diatomit-premium-10-l-sadovyy-pochvouluchshitel-organik-763402267/?at=08tYWkw0McRgB24AcyjA9z8ixmJpE1cZD7NKKumOO4Yk
B12: TRUE | C12: Цеолит вулканический | D12: https://www.ozon.ru/product/tseolit-vulkanicheskiy-dlya-rasteniy-10-litrov-2450253455/?at=gpt4WqZ5mIPyWPLqSQ6zDMEH3zLEnwcXwly97I47PjDw&from_sku=2450021403&oos_search=false
B13: TRUE | C13: Мох сфагнум | D13: https://www.ozon.ru/product/grunt-dlya-tsvetov-moh-sfagnum-sphagnum-eco-otbornyy-nasypnoy-obem-12-l-722297774/?at=nRtrLXNpKCZWV3vCJKRrrgc2QKBKEuDqpKByimgwqog&from_sku=1232520061&oos_search=false
B14: TRUE | C14: Уголь | D14: https://www.ozon.ru/product/drevesnyy-ugol-dlya-rasteniy-5l-2089930463/?at=pZtpL93EvTX2Nx4milKvrAWcmj7jj5fXyo64lSJjrzo7
B15: TRUE | C15: Биогумус | D15: https://bioabsolut.ru/biogumus-dlya-rastenij-bioabsolut.html
B16: TRUE | C16: Пеностекло | D16: https://www.ozon.ru/product/penosteklo-10-l-fraktsiya-5-10-mm-1995294238/
B17: TRUE | C17: Кора сосновая 13-19 мм | D17: https://bioabsolut.ru/cubstrat-dlya-orhidej-effect-otbornaya-galtovannaya-kora-15mm-2l.html
B18: TRUE | C18: Кора сосновая 19-28 мм | D18: https://bioabsolut.ru/cubstrat-dlya-orhidej-effect-otbornaya-galtovannaya-kora-23mm-2l.html
B19: TRUE | C19: Песок кварцевый 2-5 мм | D19: https://www.ozon.ru/product/kvartsevyy-pesok-graviy-zernistyy-dlya-zasypnyh-filtrov-2-5-mm-10-kg-3016076604/?at=46tRWZWL5TOg931vIGB9pYMc6mmR5rC1nyLPzh4BwGNm
B20: Нижняя часть горшка
C21: Дренаж
C22: Наименование | D22: Ссылка 1
B23: TRUE | C23: Размер 5-10 мм | D23: https://www.ozon.ru/product/keramzit-dlya-rasteniy-i-tsvetov-hury-5-10-mm-24l-drenazh-2353082569/?at=36tWMj37LhE0q2RLcLRZN5ZC8nxXMAhzKk0mLCl25VnK&from_sku=1550494697&oos_search=false
B24: TRUE | C24: Размер 10-20 мм | D24: https://www.ozon.ru/product/keramzit-dlya-rasteniy-i-tsvetov-hury-10-20-mm-24l-drenazh-2379141177/?at=36tWMj37LhE0q2RLcLRZN5ZC8nxXMAhzKk0mLCl25VnK&from_sku=1550494697&oos_search=false
B25: Допы
C26: Перчатки M | D26: https://www.ozon.ru/my/orderdetails/?order=0248007509-0012
C27: Корневин, 5г | D27: https://www.ozon.ru/product/lama-torf-kornevin-dlya-rasteniy-stimulyator-rosta-kornevoy-sistemy-10-sht-po-5-g-3492541872/
B28: Упаковка
C29: Дой-пак 10х15
C30: Дой-пак 12х22 | D30: https://www.ozon.ru/product/takebox-paket-doy-pak-12x22-sm-3583862063/
C31: Дой-пак 16х26 | D31: https://www.ozon.ru/product/takebox-paket-doy-pak-16x26-sm-3583861524/?from_sku=3583862063&oos_search=false
C32: Дой-пак 20х30 | D32: https://www.ozon.ru/product/takebox-paket-doy-pak-20x30-sm-3583862773/?from_sku=3583862063&oos_search=false
C33: Коробка 160×160×80 | D33: https://axelpack.ru/gofroupakovka-fefco-0427-160-160-80
C34: Коробка 200×200×100 | D34: https://axelpack.ru/gofroupakovka-fefco-0427-200-200-100
C35: Коробка 250×250×100 | D35: https://axelpack.ru/gofroupakovka-fefco-0427-250-250-100
C36: Коробка для отгрузки

Sheet Чеклист закупок
A1: ☐ | B1: Что купить | C1: Нужно | D1: Запас | E1: Итого | F1: Ед. изм. | G1: Комментарий | H1: сколько купила
A2: 🌱 КОМПОНЕНТЫ ПОЧВОСМЕСИ (запас 15%)
A3: 1 | B3: Торф нейтральный | C3: 214 | D3: +15% | E3: 246 | F3: л | G3: ~5 мешков по 50 л | H3: 250 | J3: есть
A4: 1 | B4: Торф кислый | C4: 27 | D4: +15% | E4: 31 | F4: л | G4: ~2 мешка по 20 л | H4: 60 | J4: есть
A5: 1 | B5: Кора сосновая крупная | C5: 34 | D5: +15% | E5: 40 | F5: л | G5: ~22 пакета по 5 л | H5: 20 | J5: жду
A6: 1 | B6: Кора сосновая мелкая | C6: 61 | D6: +15% | E6: 70 | F6: л | H6: 40 | J6: жду
A7: 1 | B7: Кокосовый субстрат | C7: 100 | D7: +15% | E7: 115 | F7: л | G7: ~16 брикетов по 7 л | H7: 50 | J7: есть
A8: 1 | B8: Диатомит | C8: 60 | D8: +15% | E8: 69 | F8: л | H8: 30 | J8: есть
A9: 1 | B9: Цеолит вулканический | C9: 112 | D9: +15% | E9: 129 | F9: л | G9: Тяжёлый! ~116 кг | H9: 60 | J9: жду
A10: 1 | B10: Пеностекло | C10: 61 | D10: +15% | E10: 70 | F10: л | H10: 40 | J10: есть
A11: 1 | B11: Мох сфагнум | C11: 41 | D11: +15% | E11: 47 | F11: л | G11: Лёгкий, ~2 кг | H11: 24 | J11: есть
A12: 1 | B12: Уголь | C12: 90 | D12: +15% | E12: 103 | F12: л | H12: 50 | J12: есть | K12: (на 5 больше привезли)
A13: 1 | B13: Кварцевый песок (фр. 2-5мм) | C13: 54 | D13: +15% | E13: 62 | F13: л | G13: Тяжёлый! ~93 кг | H13: 35 | J13: есть
A14: 1 | B14: Биогумус | C14: 45 | D14: +15% | E14: 52 | F14: л | H14: 30 | J14: жду
A16: 🪨 ДРЕНАЖ (запас 15%)
A17: 1 | B17: Дренаж (керамзит/пеностекло) | C17: 159 | D17: +15% | E17: 183 | F17: л | G17: ~18 мешков по 10 л, ~146 кг | H17: 96 | J17: есть
A19: 🧤 ДОПЫ (запас 10%)
A20: 1 | B20: Перчатки силиконовые | C20: 500 | D20: +10% | E20: 550 | F20: пар | G20: 500 боксов × 1 пара = 500 | H20: 250
A21: 1 | B21: Корневин (пакетик) | C21: 500 | D21: +10% | E21: 550 | F21: шт | H21: 270
A23: 📦 ДОЙ-ПАКИ TakeBox (запас 10%)
A24: ☐ | B24: Дой-пак 12×22 (грунт S + ВСЕ дренажи) | C24: 675 | D24: +10% | E24: 743 | F24: шт | G24: 175 грунт + 500 дренаж
A25: ☐ | B25: Дой-пак 16×26 (грунт M 2.2 л) | C25: 225 | D25: +10% | E25: 248 | F25: шт
A26: ☐ | B26: Дой-пак 20×30 (грунт L 3.5 л) | C26: 100 | D26: +10% | E26: 110 | F26: шт
B27: Дойпак 10х15 | J27: есть
A29: 📫 КОРОБКИ boxstore.ru (запас 10%)
A30: 1 | B30: Коробка 160×160×80 мм | C30: 175 | D30: +10% | E30: 193 | F30: шт | G30: Под боксы 1.2 л | J30: есть
A31: 1 | B31: Коробка 200×200×100 мм | C31: 225 | D31: +10% | E31: 248 | F31: шт | G31: Под боксы 2.2 л | J31: есть
A32: 1 | B32: Коробка 250×250×100 мм | C32: 100 | D32: +10% | E32: 110 | F32: шт | G32: Под боксы 3.5 л | J32: есть
A34: 🏷️ МАРКИРОВКА И ОФОРМЛЕНИЕ (запас 10%)
A35: 1 | B35: Этикетки на дой-паки | C35: 1000 | D35: +10% | E35: 1100 | F35: шт | G35: 2 на бокс (грунт + дренаж)
A36: 1 | B36: Гайд-стикеры | C36: 500 | D36: +10% | E36: 550 | F36: шт | G36: 7 видов × ~80 шт
A37: 1 | B37: Этикетки Ozon (штрих-код) | C37: 500 | D37: +10% | E37: 550 | F37: шт | G37: Печать из ЛК, термопринтер
A39: 🚚 ТРАНСПОРТНАЯ УПАКОВКА для Ozon FBO (запас 10%)
A40: 1 | B40: Гофрокороба 600×400×400 мм | C40: 40 | D40: +10% | E40: 46 | F40: шт | G40: ~12-15 боксов в один короб | J40: есть
A41: 1 | B41: Скотч упаковочный | C41: 3 | D41: +10% | E41: 3 | F41: рулонов | J41: есть
A43: 🗄️ ХРАНЕНИЕ КОМПОНЕНТОВ (разовая покупка)
A44: 1 | B44: Контейнер Roxbox 50 л на колёсах | C44: 7 | D44: +0% | E44: 7 | F44: шт | G44: Для торф×2, кокос, биогумус, сфагнум, кора, дренаж | J44: есть
A45: 1 | B45: Ящики для сухих компонентов | C45: 5 | D45: +0% | E45: 5 | F45: шт | G45: Для цеолит, песок, диатомит, уголь, пеностекло | J45: есть
A47: 🔧 ИНСТРУМЕНТЫ (разовая покупка)
A48: 1 | B48: Запайщик пакетов импульсный | C48: 1 | D48: +0% | E48: 1 | F48: шт | G48: 1500-3000 ₽, Ozon | J48: есть
A49: 1 | B49: Весы кухонные (до 10 кг) | C49: 1 | D49: +0% | E49: 1 | F49: шт | J49: есть
A50: 1 | B50: Мерные ёмкости (0.5, 1, 2 л) | C50: 3 | D50: +0% | E50: 3 | F50: шт | J50: есть
A51: 1 | B51: Тазы для замешивания 10-15 л | C51: 2 | D51: +0% | E51: 2 | F51: шт
A52: 1 | B52: Термопринтер для этикеток | C52: 1 | D52: +0% | E52: 1 | F52: шт | G52: Для маркировки Ozon | J52: есть
A53: 1 | B53: Совки мерные | C53: 2 | D53: +0% | E53: 2 | F53: шт | J53: есть
A55: 📊 СВОДКА
B56: Почвосмесь: | C56: 11 компонентов, ~1032 л с запасом 15%, ~467 кг
B57: Дренаж: | C57: ~183 л с запасом 15%, ~146 кг
B58: Общий вес сырья: | C58: ~614 кг
B59: Допы: | C59: 1100 пар перчаток + 550 корневинов (с запасом 10%)
B60: Дой-паки: | C60: 743 + 248 + 110 = ~1100 шт (с запасом 10%)
B61: Коробки: | C61: 193 + 248 + 110 = ~551 шт (с запасом 10%)
B62: Курьерские пакеты: | C62: НЕ НУЖНЫ — Ozon FBO упаковывает сам
B63: Транспортные короба: | C63: ~44 шт
B64: Контейнеры хранения: | C64: ~12 шт (разовая покупка)
B65: Инструменты: | C65: запайщик, весы, термопринтер, мерные ёмкости

Sheet Размеры горшков
A1: Группа | B1: Растение | C1: S (9–10 см) | G1: M (12–14 см) | K1: L (17–19 см) | O1: XL (21–24 см) | S1: XXL (27–30 см)
C2: ⌀ см | D2: Высота см | E2: Объём л | F2: Подходит | G2: ⌀ см | H2: Высота см | I2: Объём л | J2: Подходит | K2: ⌀ см | L2: Высота см | M2: Объём л | N2: Подходит | O2: ⌀ см | P2: Высота см | Q2: Объём л | R2: Подходит | S2: ⌀ см | T2: Высота см | U2: Объём л | V2: Подходит
A3: Ароидные | B3: Сциндапсус | C3: 9–10 | D3: 9–11 | E3: 0.4–0.6 | F3: ✓ | G3: 12–14 | H3: 12–15 | I3: 1.0–1.8 | J3: ★ | K3: 17–19 | L3: 17–20 | M3: 2.5–4.0 | N3: ✓
B4: Алоказия | G4: 12–14 | H4: 12–15 | I4: 1.0–1.8 | J4: ✓ | K4: 17–19 | L4: 17–20 | M4: 2.5–4.0 | N4: ★ | O4: 21–24 | P4: 21–25 | Q4: 5.0–8.0 | R4: ✓
B5: Аглаонема | C5: 9–10 | D5: 9–11 | E5: 0.4–0.6 | F5: ✓ | G5: 12–14 | H5: 12–15 | I5: 1.0–1.8 | J5: ★ | K5: 17–19 | L5: 17–20 | M5: 2.5–4.0 | N5: ✓
B6: Монстера | G6: 12–14 | H6: 12–15 | I6: 1.0–1.8 | J6: ✓ | K6: 17–19 | L6: 17–20 | M6: 2.5–4.0 | N6: ✓ | O6: 21–24 | P6: 21–25 | Q6: 5.0–8.0 | R6: ★ | S6: 27–30 | T6: 27–32 | U6: 10.0–15.0 | V6: ✓
B7: Замиокулькас | C7: 9–10 | D7: 9–11 | E7: 0.4–0.6 | F7: ✓ | G7: 12–14 | H7: 12–15 | I7: 1.0–1.8 | J7: ✓ | K7: 17–19 | L7: 17–20 | M7: 2.5–4.0 | N7: ★ | O7: 21–24 | P7: 21–25 | Q7: 5.0–8.0 | R7: ✓
B8: Антуриум | C8: 9–10 | D8: 9–11 | E8: 0.4–0.6 | F8: ✓ | G8: 12–14 | H8: 12–15 | I8: 1.0–1.8 | J8: ★ | K8: 17–19 | L8: 17–20 | M8: 2.5–4.0 | N8: ✓
B9: Спатифиллум | C9: 9–10 | D9: 9–11 | E9: 0.4–0.6 | F9: ✓ | G9: 12–14 | H9: 12–15 | I9: 1.0–1.8 | J9: ✓ | K9: 17–19 | L9: 17–20 | M9: 2.5–4.0 | N9: ★ | O9: 21–24 | P9: 21–25 | Q9: 5.0–8.0 | R9: ✓
B10: Филодендрон | G10: 12–14 | H10: 12–15 | I10: 1.0–1.8 | J10: ✓ | K10: 17–19 | L10: 17–20 | M10: 2.5–4.0 | N10: ★ | O10: 21–24 | P10: 21–25 | Q10: 5.0–8.0 | R10: ✓
B11: Эпипремнум | C11: 9–10 | D11: 9–11 | E11: 0.4–0.6 | F11: ✓ | G11: 12–14 | H11: 12–15 | I11: 1.0–1.8 | J11: ★ | K11: 17–19 | L11: 17–20 | M11: 2.5–4.0 | N11: ✓
A12: Кутровые | B12: Хойя | C12: 9–10 | D12: 9–11 | E12: 0.4–0.6 | F12: ✓ | G12: 12–14 | H12: 12–15 | I12: 1.0–1.8 | J12: ★ | K12: 17–19 | L12: 17–20 | M12: 2.5–4.0 | N12: ✓
B13: Церопегия | C13: 9–10 | D13: 9–11 | E13: 0.4–0.6 | F13: ★ | G13: 12–14 | H13: 12–15 | I13: 1.0–1.8 | J13: ✓
A14: Марантовые | B14: Калатея | C14: 9–10 | D14: 9–11 | E14: 0.4–0.6 | F14: ✓ | G14: 12–14 | H14: 12–15 | I14: 1.0–1.8 | J14: ★ | K14: 17–19 | L14: 17–20 | M14: 2.5–4.0 | N14: ✓
A15: Папоротники | C15: 9–10 | D15: 9–11 | E15: 0.4–0.6 | F15: ✓ | G15: 12–14 | H15: 12–15 | I15: 1.0–1.8 | J15: ★ | K15: 17–19 | L15: 17–20 | M15: 2.5–4.0 | N15: ✓
A16: Спаржевые | B16: Аспидистра | G16: 12–14 | H16: 12–15 | I16: 1.0–1.8 | J16: ✓ | K16: 17–19 | L16: 17–20 | M16: 2.5–4.0 | N16: ★ | O16: 21–24 | P16: 21–25 | Q16: 5.0–8.0 | R16: ✓
B17: Сансевиерия | C17: 9–10 | D17: 9–11 | E17: 0.4–0.6 | F17: ✓ | G17: 12–14 | H17: 12–15 | I17: 1.0–1.8 | J17: ✓ | K17: 17–19 | L17: 17–20 | M17: 2.5–4.0 | N17: ★ | O17: 21–24 | P17: 21–25 | Q17: 5.0–8.0 | R17: ✓
B18: Хлорофитум | C18: 9–10 | D18: 9–11 | E18: 0.4–0.6 | F18: ✓ | G18: 12–14 | H18: 12–15 | I18: 1.0–1.8 | J18: ★ | K18: 17–19 | L18: 17–20 | M18: 2.5–4.0 | N18: ✓
B19: Драцена | G19: 12–14 | H19: 12–15 | I19: 1.0–1.8 | J19: ✓ | K19: 17–19 | L19: 17–20 | M19: 2.5–4.0 | N19: ✓ | O19: 21–24 | P19: 21–25 | Q19: 5.0–8.0 | R19: ★ | S19: 27–30 | T19: 27–32 | U19: 10.0–15.0 | V19: ✓
A20: Банановые | B20: Стрелиция | K20: 17–19 | L20: 17–20 | M20: 2.5–4.0 | N20: ✓ | O20: 21–24 | P20: 21–25 | Q20: 5.0–8.0 | R20: ★ | S20: 27–30 | T20: 27–32 | U20: 10.0–15.0 | V20: ✓
A21: Агавовые | B21: Юкка | G21: 12–14 | H21: 12–15 | I21: 1.0–1.8 | J21: ✓ | K21: 17–19 | L21: 17–20 | M21: 2.5–4.0 | N21: ✓ | O21: 21–24 | P21: 21–25 | Q21: 5.0–8.0 | R21: ★ | S21: 27–30 | T21: 27–32 | U21: 10.0–15.0 | V21: ✓
A22: Пальмы | B22: Хамедорея | G22: 12–14 | H22: 12–15 | I22: 1.0–1.8 | J22: ✓ | K22: 17–19 | L22: 17–20 | M22: 2.5–4.0 | N22: ★ | O22: 21–24 | P22: 21–25 | Q22: 5.0–8.0 | R22: ✓
B23: Ховея | K23: 17–19 | L23: 17–20 | M23: 2.5–4.0 | N23: ✓ | O23: 21–24 | P23: 21–25 | Q23: 5.0–8.0 | R23: ★ | S23: 27–30 | T23: 27–32 | U23: 10.0–15.0 | V23: ✓
A24: Тутовые | B24: Фикусы | C24: 9–10 | D24: 9–11 | E24: 0.4–0.6 | F24: ✓ | G24: 12–14 | H24: 12–15 | I24: 1.0–1.8 | J24: ✓ | K24: 17–19 | L24: 17–20 | M24: 2.5–4.0 | N24: ★ | O24: 21–24 | P24: 21–25 | Q24: 5.0–8.0 | R24: ✓ | S24: 27–30 | T24: 27–32 | U24: 10.0–15.0 | V24: ✓
A25: Аралиевые | B25: Шеффлера | G25: 12–14 | H25: 12–15 | I25: 1.0–1.8 | J25: ✓ | K25: 17–19 | L25: 17–20 | M25: 2.5–4.0 | N25: ★ | O25: 21–24 | P25: 21–25 | Q25: 5.0–8.0 | R25: ✓
A26: Суккуленты | C26: 9–10 | D26: 9–11 | E26: 0.4–0.6 | F26: ★ | G26: 12–14 | H26: 12–15 | I26: 1.0–1.8 | J26: ✓
A27: Цитрусовые | G27: 12–14 | H27: 12–15 | I27: 1.0–1.8 | J27: ✓ | K27: 17–19 | L27: 17–20 | M27: 2.5–4.0 | N27: ★ | O27: 21–24 | P27: 21–25 | Q27: 5.0–8.0 | R27: ✓
A28: Геснериевые | B28: Фиалки | C28: 9–10 | D28: 9–11 | E28: 0.4–0.6 | F28: ★ | G28: 12–14 | H28: 12–15 | I28: 1.0–1.8 | J28: ✓
A33: Обозначения:
A34: ★ — самый популярный размер для данного растения
A35: ✓ — подходящий размер
B39: литраж
B40: S | C40: 0.6
B41: M | C41: 1.2
C42: 1.8
C43: 2.2
B44: L | C44: 3
C45: 3.5
C46: 4
B47: XL | C47: 5
C48: 6
